cxdepy/__init__.py
cxdepy/demo1.py
cxdepy/demo2.py
cxdepy-1.0.dist-info/METADATA
cxdepy-1.0.dist-info/WHEEL
cxdepy-1.0.dist-info/top_level.txt
cxdepy-1.0.dist-info/RECORD
