Metadata-Version: 2.1
Name: cxdepy
Version: 1.0
Summary: 这是第一个对外发布的模块
Author: cx
Author-email: 404431634@qq.com
License: UNKNOWN
Platform: UNKNOWN
